sp_on_prem/__init__.py
sp_on_prem/sp_handler.py
sharepoint_on_prem-0.0.1.dist-info/METADATA
sharepoint_on_prem-0.0.1.dist-info/WHEEL
sharepoint_on_prem-0.0.1.dist-info/top_level.txt
sharepoint_on_prem-0.0.1.dist-info/RECORD
