Metadata-Version: 2.1
Name: sharepoint-on-prem
Version: 0.0.1
Summary: UNKNOWN
Home-page: UNKNOWN
Author: Shimeng Zhao
Author-email: zhaoshimeng2015@gmail.com
License: UNKNOWN
Platform: UNKNOWN
Requires-Dist: requests-ntlm2
